{
  "userlogin": [
    {
      "username": "HARITA",
      "password": "INDIA",
      "login": 0,
      "id": 2
    },
    {
      "username": "RANITA",
      "password": "NAGARAJ123",
      "login": 0,
      "id": 4
    },
    {
      "username": "HARISH",
      "password": "HARISH123",
      "login": 0,
      "id": 14
    },
    {
      "username": "vasanth",
      "password": "vasanth123 ",
      "id": 15
    },
    {
      "username": "DHANAPRAKASH",
      "password": "DHANAPRAKASH123",
      "id": 17
    },
    {
      "username": "Umarani",
      "password": "uma@123",
      "id": 18
    }
  ],
  "adminlogin": [
    {
      "aname": "vasanth",
      "apassword": "vasanth123",
      "login": 0
    }
  ],
  "Twittermessage": [
    {
      "twittmsg":""
    }
  ]
}