{
  "userlogin": [
    {
      "username": "HARITA",
      "password": "INDIA",
      "login": 0,
      "id": 2
    },
    {
      "username": "RANITA",
      "password": "NAGARAJ123",
      "login": 0,
      "id": 4
    },
    {
      "username": "HARISH",
      "password": "HARISH123",
      "login": 0,
      "id": 14
    },
    {
      "username": "vasanth",
      "password": "vasanth123 ",
      "id": 15
    },
    {
      "username": "DHANAPRAKASH",
      "password": "DHANAPRAKASH123",
      "id": 17
    },
    {
      "username": "Umarani",
      "password": "uma@123",
      "id": 18
    }
  ],
  "adminlogin": [
    {
      "aname": "vasanth",
      "apassword": "vasanth123",
      "login": 0
    }
  ],
  "Twittermessage": [
    {
      "id": 1
    },
    {
      "twittmsg": "hello harita",
      "id": 2
    },
    {
      "twittmsg": "hello harita",
      "id": 3
    },
    {
      "twittmsg": "hello ranita",
      "id": 4
    },
    {
      "user_id": "18",
      "user_name": "Umarani",
      "twittmsg": "hello harita",
      "id": 5
    },
    {
      "user_id": "14",
      "user_name": "HARISH",
      "twittmsg": "hello harish",
      "sender_uid": "2",
      "sender_username": "HARITA",
      "id": 6
    },
    {
      "user_id": "14",
      "user_name": "HARISH",
      "twittmsg": "hello harish",
      "sender_uid": "2",
      "sender_username": "HARITA",
      "id": 7
    },
    {
      "user_id": "19",
      "user_name": "YAMINI",
      "twittmsg": "hello ranita",
      "sender_uid": "19",
      "sender_username": "YAMINI",
      "id": 8
    },
    {
      "user_id": "4",
      "user_name": "RANITA",
      "twittmsg": "hello harish",
      "sender_uid": "19",
      "sender_username": "YAMINI",
      "id": 9
    }
  ]
}